test/__init__.py
test/test_aggrigation_field.py
test/test_api_response.py
test/test_data_api.py
test/test_data_api_response.py
test/test_data_message.py
test/test_data_store_request.py
test/test_doc_store_item.py
test/test_filter_field.py
test/test_map_object.py
test/test_search_api.py
test/test_search_request.py
xrely_lib_client/__init__.py
xrely_lib_client/api_client.py
xrely_lib_client/configuration.py
xrely_lib_client/rest.py
xrely_lib_client/api/__init__.py
xrely_lib_client/api/data_api.py
xrely_lib_client/api/search_api.py
xrely_lib_client/models/__init__.py
xrely_lib_client/models/aggrigation_field.py
xrely_lib_client/models/api_response.py
xrely_lib_client/models/data_api_response.py
xrely_lib_client/models/data_message.py
xrely_lib_client/models/data_store_request.py
xrely_lib_client/models/doc_store_item.py
xrely_lib_client/models/filter_field.py
xrely_lib_client/models/map_object.py
xrely_lib_client/models/search_request.py
xrely_lib_client-1.0.0.dist-info/LICENSE
xrely_lib_client-1.0.0.dist-info/METADATA
xrely_lib_client-1.0.0.dist-info/WHEEL
xrely_lib_client-1.0.0.dist-info/top_level.txt
xrely_lib_client-1.0.0.dist-info/RECORD
