Metadata-Version: 2.1
Name: xrely-lib-client
Version: 1.0.0
Summary: client library for xrely platform.
Home-page: https://www.xrely.com
Author: team xrely
Author-email: info@xrely.com
License: UNKNOWN
Keywords: Web search intelligence,Autocrawl search,Intelligent search engine,install site search,Autocomplete search solution,Autocrawl Search,Search discovery
Platform: UNKNOWN
License-File: LICENSE
Requires-Dist: certifi (>=2017.4.17)
Requires-Dist: python-dateutil (>=2.1)
Requires-Dist: six (>=1.10)
Requires-Dist: urllib3 (>=1.23)
